[
  {
      "id": 1,
      "checked": false,
      "bookStatus": 3,
      "contactsAreaCode": null,
      "custInfo": {
          "natureCustId": "90857921",
          "natureCustName": "天津润康科技有限公司",
          "listCustCode": "",
          "staffSize": null,
          "companyStaffSize": "",
          "areaStaffSize": "12"
      },
      "iphoneInfo": {
          "contactsCreateOaId": null,
          "contactsCreateOaName": null,
          "contactsCreateTag": null,
          "contactsAreaName": "塘沽区",
          "createTime": "2024-11-07 00:00:00",
          "operTime": "",
          "staffPhoneNums": "2",
          "staffCompanyIdPhoneNums": "2",
          "staffCompanyPayPhoneNums": "0",
          "staffCompanyRhPhoneNums": "0",
          "payImpNums": "0"
      },
      "cards": {
          "checkCucNums": 0,
          "checkCmcNums": 0,
          "checkCtcNums": 0,
          "checkOthNums": 0,
          "companyCucRate": null,
          "companyCmcRate": null,
          "companyCtcRate": null,
          "companyOthRate": null,
          "areaCucRate": "16.67%",
          "areaCmcRate": "0%",
          "areaCtcRate": "0%",
          "areaOthRate": "0%"
      },
      "ableUpdate": "2",
      "jobId": "pansd1",
      "marketUnitName": "塘沽"
  },
  {
      "id": 2,
      "checked": false,
      "bookStatus": 3,
      "contactsAreaCode": null,
      "custInfo": {
          "natureCustId": "101152389",
          "natureCustName": "烟台高凯船舶维护技术咨询有限公司",
          "listCustCode": "",
          "staffSize": "2",
          "companyStaffSize": "",
          "areaStaffSize": "10"
      },
      "iphoneInfo": {
          "contactsCreateOaId": "tj-sunxin",
          "contactsCreateOaName": "孙鑫",
          "contactsCreateTag": "营销单位-要客经理",
          "contactsAreaName": "塘沽区",
          "createTime": "2024-11-07 00:00:00",
          "operTime": "",
          "staffPhoneNums": "37",
          "staffCompanyIdPhoneNums": "21",
          "staffCompanyPayPhoneNums": "0",
          "staffCompanyRhPhoneNums": "0",
          "payImpNums": "15"
      },
      "cards": {
          "checkCucNums": 0,
          "checkCmcNums": 1,
          "checkCtcNums": 0,
          "checkOthNums": 0,
          "companyCucRate": null,
          "companyCmcRate": null,
          "companyCtcRate": null,
          "companyOthRate": null,
          "areaCucRate": "100%",
          "areaCmcRate": "10%",
          "areaCtcRate": "0%",
          "areaOthRate": "0%"
      },
      "ableUpdate": "2",
      "jobId": "tj-sunxin",
      "marketUnitName": "塘沽"
  },
  {
      "id": 3,
      "checked": false,
      "bookStatus": 3,
      "contactsAreaCode": null,
      "custInfo": {
          "natureCustId": "104622704",
          "natureCustName": "北京摩恩科技有限责任公司",
          "listCustCode": "020291000288",
          "staffSize": "3",
          "companyStaffSize": "0",
          "areaStaffSize": "0"
      },
      "iphoneInfo": {
          "contactsCreateOaId": null,
          "contactsCreateOaName": null,
          "contactsCreateTag": null,
          "contactsAreaName": "数智",
          "createTime": "2024-11-07 00:00:00",
          "operTime": "",
          "staffPhoneNums": "0",
          "staffCompanyIdPhoneNums": "0",
          "staffCompanyPayPhoneNums": "0",
          "staffCompanyRhPhoneNums": "0",
          "payImpNums": "0"
      },
      "cards": {
          "checkCucNums": 0,
          "checkCmcNums": 0,
          "checkCtcNums": 0,
          "checkOthNums": 0,
          "companyCucRate": null,
          "companyCmcRate": null,
          "companyCtcRate": null,
          "companyOthRate": null,
          "areaCucRate": null,
          "areaCmcRate": null,
          "areaCtcRate": null,
          "areaOthRate": null
      },
      "ableUpdate": "2",
      "jobId": "luoc56",
      "marketUnitName": "数智中心"
  },
  {
      "id": 4,
      "checked": false,
      "bookStatus": 3,
      "contactsAreaCode": null,
      "custInfo": {
          "natureCustId": "109993340",
          "natureCustName": "北京泰氪科技发展有限公司",
          "listCustCode": "021300086475",
          "staffSize": "0",
          "companyStaffSize": "",
          "areaStaffSize": "40"
      },
      "iphoneInfo": {
          "contactsCreateOaId": "zhenglin7",
          "contactsCreateOaName": "郑琳",
          "contactsCreateTag": "营销单位-要客经理",
          "contactsAreaName": "塘沽区",
          "createTime": "2024-11-07 00:00:00",
          "operTime": "",
          "staffPhoneNums": "4",
          "staffCompanyIdPhoneNums": "0",
          "staffCompanyPayPhoneNums": "0",
          "staffCompanyRhPhoneNums": "0",
          "payImpNums": "2"
      },
      "cards": {
          "checkCucNums": 0,
          "checkCmcNums": 2,
          "checkCtcNums": 0,
          "checkOthNums": 0,
          "companyCucRate": null,
          "companyCmcRate": null,
          "companyCtcRate": null,
          "companyOthRate": null,
          "areaCucRate": "5%",
          "areaCmcRate": "5%",
          "areaCtcRate": "0%",
          "areaOthRate": "0%"
      },
      "ableUpdate": "2",
      "jobId": "zhenglin7",
      "marketUnitName": "塘沽"
  },
  {
      "id": 5,
      "checked": false,
      "bookStatus": 3,
      "contactsAreaCode": null,
      "custInfo": {
          "natureCustId": "115274902",
          "natureCustName": "山东浪潮智慧空间技术服务有限公司",
          "listCustCode": "",
          "staffSize": null,
          "companyStaffSize": "30",
          "areaStaffSize": "30"
      },
      "iphoneInfo": {
          "contactsCreateOaId": "zhangjb48",
          "contactsCreateOaName": "张劲博",
          "contactsCreateTag": "营销单位-要客经理",
          "contactsAreaName": "河东区",
          "createTime": "2024-11-07 00:00:00",
          "operTime": "",
          "staffPhoneNums": "5",
          "staffCompanyIdPhoneNums": "0",
          "staffCompanyPayPhoneNums": "0",
          "staffCompanyRhPhoneNums": "0",
          "payImpNums": "3"
      },
      "cards": {
          "checkCucNums": 2,
          "checkCmcNums": 0,
          "checkCtcNums": 0,
          "checkOthNums": 0,
          "companyCucRate": "16.67%",
          "companyCmcRate": "0%",
          "companyCtcRate": "0%",
          "companyOthRate": "0%",
          "areaCucRate": "16.67%",
          "areaCmcRate": "0%",
          "areaCtcRate": "0%",
          "areaOthRate": "0%"
      },
      "ableUpdate": "2",
      "jobId": "zhangjb48",
      "marketUnitName": "河东"
  },
  {
      "id": 6,
      "checked": false,
      "bookStatus": 3,
      "contactsAreaCode": null,
      "custInfo": {
          "natureCustId": "120184377",
          "natureCustName": "光瑞聚耀(北京)财富资产管理有限公司",
          "listCustCode": "",
          "staffSize": "50",
          "companyStaffSize": "7",
          "areaStaffSize": "7"
      },
      "iphoneInfo": {
          "contactsCreateOaId": "liuyz75",
          "contactsCreateOaName": "刘誉朝",
          "contactsCreateTag": "营销单位-要客经理",
          "contactsAreaName": "和平区",
          "createTime": "2024-11-07 00:00:00",
          "operTime": "",
          "staffPhoneNums": "6",
          "staffCompanyIdPhoneNums": "0",
          "staffCompanyPayPhoneNums": "0",
          "staffCompanyRhPhoneNums": "0",
          "payImpNums": "5"
      },
      "cards": {
          "checkCucNums": 0,
          "checkCmcNums": 1,
          "checkCtcNums": 0,
          "checkOthNums": 0,
          "companyCucRate": "71.43%",
          "companyCmcRate": "14.29%",
          "companyCtcRate": "0%",
          "companyOthRate": "0%",
          "areaCucRate": "71.43%",
          "areaCmcRate": "14.29%",
          "areaCtcRate": "0%",
          "areaOthRate": "0%"
      },
      "ableUpdate": "2",
      "jobId": "liuyz75",
      "marketUnitName": "和平"
  },
  {
      "id": 7,
      "checked": false,
      "bookStatus": 3,
      "contactsAreaCode": null,
      "custInfo": {
          "natureCustId": "126601887",
          "natureCustName": "天津(滨海)人工智能创新中心",
          "listCustCode": "021300083708",
          "staffSize": null,
          "companyStaffSize": "",
          "areaStaffSize": "60"
      },
      "iphoneInfo": {
          "contactsCreateOaId": "tj-zhuzh",
          "contactsCreateOaName": "朱振华",
          "contactsCreateTag": "营销单位-要客经理",
          "contactsAreaName": "塘沽区",
          "createTime": "2024-11-07 00:00:00",
          "operTime": "",
          "staffPhoneNums": "11",
          "staffCompanyIdPhoneNums": "0",
          "staffCompanyPayPhoneNums": "0",
          "staffCompanyRhPhoneNums": "0",
          "payImpNums": "9"
      },
      "cards": {
          "checkCucNums": 1,
          "checkCmcNums": 0,
          "checkCtcNums": 1,
          "checkOthNums": 0,
          "companyCucRate": null,
          "companyCmcRate": null,
          "companyCtcRate": null,
          "companyOthRate": null,
          "areaCucRate": "16.67%",
          "areaCmcRate": "0%",
          "areaCtcRate": "1.67%",
          "areaOthRate": "0%"
      },
      "ableUpdate": "2",
      "jobId": "tj-zhuzh",
      "marketUnitName": "塘沽"
  },
  {
      "id": 8,
      "checked": false,
      "bookStatus": 3,
      "contactsAreaCode": null,
      "custInfo": {
          "natureCustId": "126605351",
          "natureCustName": "天津市河东区住房保障服务中心",
          "listCustCode": "020491001255",
          "staffSize": "0",
          "companyStaffSize": "30",
          "areaStaffSize": "30"
      },
      "iphoneInfo": {
          "contactsCreateOaId": "liulei93",
          "contactsCreateOaName": "刘磊",
          "contactsCreateTag": null,
          "contactsAreaName": "河东区",
          "createTime": "2024-11-07 00:00:00",
          "operTime": "",
          "staffPhoneNums": "17",
          "staffCompanyIdPhoneNums": "3",
          "staffCompanyPayPhoneNums": "0",
          "staffCompanyRhPhoneNums": "0",
          "payImpNums": "14"
      },
      "cards": {
          "checkCucNums": 0,
          "checkCmcNums": 0,
          "checkCtcNums": 0,
          "checkOthNums": 0,
          "companyCucRate": "56.67%",
          "companyCmcRate": "0%",
          "companyCtcRate": "0%",
          "companyOthRate": "0%",
          "areaCucRate": "56.67%",
          "areaCmcRate": "0%",
          "areaCtcRate": "0%",
          "areaOthRate": "0%"
      },
      "ableUpdate": "2",
      "jobId": "liulei93",
      "marketUnitName": "河东"
  },
  {
      "id": 9,
      "checked": false,
      "bookStatus": 3,
      "contactsAreaCode": null,
      "custInfo": {
          "natureCustId": "126609120",
          "natureCustName": "天津市宝坻区农业发展服务中心",
          "listCustCode": "021700000040",
          "staffSize": "0",
          "companyStaffSize": "",
          "areaStaffSize": "121"
      },
      "iphoneInfo": {
          "contactsCreateOaId": "sunxy1109",
          "contactsCreateOaName": "孙学妍",
          "contactsCreateTag": "营销单位-要客经理",
          "contactsAreaName": "宝坻区",
          "createTime": "2024-11-07 00:00:00",
          "operTime": "",
          "staffPhoneNums": "106",
          "staffCompanyIdPhoneNums": "36",
          "staffCompanyPayPhoneNums": "0",
          "staffCompanyRhPhoneNums": "0",
          "payImpNums": "69"
      },
      "cards": {
          "checkCucNums": 1,
          "checkCmcNums": 0,
          "checkCtcNums": 0,
          "checkOthNums": 0,
          "companyCucRate": null,
          "companyCmcRate": null,
          "companyCtcRate": null,
          "companyOthRate": null,
          "areaCucRate": "87.6%",
          "areaCmcRate": "0%",
          "areaCtcRate": "0%",
          "areaOthRate": "0%"
      },
      "ableUpdate": "2",
      "jobId": "sunxy1109",
      "marketUnitName": "宝坻"
  },
  {
      "id": 10,
      "checked": false,
      "bookStatus": 3,
      "contactsAreaCode": null,
      "custInfo": {
          "natureCustId": "126613030",
          "natureCustName": "天津市宝坻区河长制事务中心",
          "listCustCode": "021700111642",
          "staffSize": "0",
          "companyStaffSize": "",
          "areaStaffSize": "251"
      },
      "iphoneInfo": {
          "contactsCreateOaId": "wangdd5630",
          "contactsCreateOaName": "王丹丹",
          "contactsCreateTag": "营销单位-要客经理",
          "contactsAreaName": "宝坻区",
          "createTime": "2024-11-07 00:00:00",
          "operTime": "",
          "staffPhoneNums": "48",
          "staffCompanyIdPhoneNums": "38",
          "staffCompanyPayPhoneNums": "0",
          "staffCompanyRhPhoneNums": "0",
          "payImpNums": "9"
      },
      "cards": {
          "checkCucNums": 1,
          "checkCmcNums": 0,
          "checkCtcNums": 0,
          "checkOthNums": 0,
          "companyCucRate": null,
          "companyCmcRate": null,
          "companyCtcRate": null,
          "companyOthRate": null,
          "areaCucRate": "19.12%",
          "areaCmcRate": "0%",
          "areaCtcRate": "0%",
          "areaOthRate": "0%"
      },
      "ableUpdate": "2",
      "jobId": "wangdd5630",
      "marketUnitName": "宝坻"
  },
  {},
  {}
]